kubeflow/__init__.py
kubeflow/training/__init__.py
kubeflow/training/api_client.py
kubeflow/training/configuration.py
kubeflow/training/exceptions.py
kubeflow/training/rest.py
kubeflow/training/api/__init__.py
kubeflow/training/api/py_torch_job_client.py
kubeflow/training/api/py_torch_job_watch.py
kubeflow/training/api/tf_job_client.py
kubeflow/training/api/tf_job_watch.py
kubeflow/training/constants/__init__.py
kubeflow/training/constants/constants.py
kubeflow/training/models/__init__.py
kubeflow/training/models/v1_elastic_policy.py
kubeflow/training/models/v1_job_condition.py
kubeflow/training/models/v1_job_status.py
kubeflow/training/models/v1_mx_job.py
kubeflow/training/models/v1_mx_job_list.py
kubeflow/training/models/v1_mx_job_spec.py
kubeflow/training/models/v1_py_torch_job.py
kubeflow/training/models/v1_py_torch_job_list.py
kubeflow/training/models/v1_py_torch_job_spec.py
kubeflow/training/models/v1_rdzv_conf.py
kubeflow/training/models/v1_replica_spec.py
kubeflow/training/models/v1_replica_status.py
kubeflow/training/models/v1_run_policy.py
kubeflow/training/models/v1_scheduling_policy.py
kubeflow/training/models/v1_tf_job.py
kubeflow/training/models/v1_tf_job_list.py
kubeflow/training/models/v1_tf_job_spec.py
kubeflow/training/models/v1_xg_boost_job.py
kubeflow/training/models/v1_xg_boost_job_list.py
kubeflow/training/models/v1_xg_boost_job_spec.py
kubeflow/training/utils/__init__.py
kubeflow/training/utils/utils.py
test/__init__.py
test/test_v1_elastic_policy.py
test/test_v1_job_condition.py
test/test_v1_job_status.py
test/test_v1_mx_job.py
test/test_v1_mx_job_list.py
test/test_v1_mx_job_spec.py
test/test_v1_py_torch_job.py
test/test_v1_py_torch_job_list.py
test/test_v1_py_torch_job_spec.py
test/test_v1_rdzv_conf.py
test/test_v1_replica_spec.py
test/test_v1_replica_status.py
test/test_v1_run_policy.py
test/test_v1_scheduling_policy.py
test/test_v1_tf_job.py
test/test_v1_tf_job_list.py
test/test_v1_tf_job_spec.py
test/test_v1_xg_boost_job.py
kubeflow_training_7761578-1.4.0.dist-info/METADATA
kubeflow_training_7761578-1.4.0.dist-info/WHEEL
kubeflow_training_7761578-1.4.0.dist-info/top_level.txt
kubeflow_training_7761578-1.4.0.dist-info/RECORD
