Metadata-Version: 2.1
Name: kubeflow-training-7761578
Version: 1.4.0
Summary: Training Operator Python SDK
Home-page: https://github.com/kubeflow/training-operator/sdk/python
Author: Kubeflow Authors
Author-email: hejinchi@cn.ibm.com
License: Apache License Version 2.0
Classifier: Intended Audience :: Developers
Classifier: Intended Audience :: Education
Classifier: Intended Audience :: Science/Research
Classifier: Programming Language :: Python :: 3
Classifier: Programming Language :: Python :: 3.6
Classifier: Programming Language :: Python :: 3.7
Classifier: License :: OSI Approved :: Apache Software License
Classifier: Operating System :: OS Independent
Classifier: Topic :: Scientific/Engineering
Classifier: Topic :: Scientific/Engineering :: Artificial Intelligence
Classifier: Topic :: Software Development
Classifier: Topic :: Software Development :: Libraries
Classifier: Topic :: Software Development :: Libraries :: Python Modules
Requires-Dist: certifi (>=14.05.14)
Requires-Dist: six (>=1.10)
Requires-Dist: python-dateutil (>=2.5.3)
Requires-Dist: setuptools (>=21.0.0)
Requires-Dist: urllib3 (>=1.15.1)
Requires-Dist: kubernetes (>=12.0.0)
Requires-Dist: retrying (>=1.3.3)
Provides-Extra: test
Requires-Dist: pytest ; extra == 'test'
Requires-Dist: pytest-tornasync ; extra == 'test'
Requires-Dist: mypy ; extra == 'test'
